common/__init__.py
common/code_helper.py
common/dictfetch_helper.py
common/file_upload_helper.py
common/format_date.py
common/pagination_helper.py
common/pdf_helper.py
common/transaction_helper.py
common/templates/__init__.py
fusiox-0.1.0.dist-info/LICENSE
fusiox-0.1.0.dist-info/METADATA
fusiox-0.1.0.dist-info/WHEEL
fusiox-0.1.0.dist-info/top_level.txt
fusiox-0.1.0.dist-info/RECORD
