Metadata-Version: 2.1
Name: fusiox
Version: 0.1.0
Summary: This super package is called fusiox.
Home-page: https://github.com/alexsirait/fusiox
Author: Alex Sirait
Author-email: alexsirait1001@gmail.com
Classifier: Programming Language :: Python :: 3
Classifier: License :: OSI Approved :: MIT License
Classifier: Operating System :: OS Independent
Requires-Python: >=3.2
License-File: LICENSE
